ptf/__init__.py
ptf/_version.py
ptf/afpacket.py
ptf/base_tests.py
ptf/dataplane.py
ptf/mask.py
ptf/netutils.py
ptf/packet.py
ptf/packet_scapy.py
ptf/parse.py
ptf/pcap_writer.py
ptf/ptfutils.py
ptf/testutils.py
ptf/thriftutils.py
ptf/platforms/__init__.py
ptf/platforms/dummy.py
ptf/platforms/eth.py
ptf/platforms/local.py
ptf/platforms/nn.py
ptf/platforms/remote.py
ptf-0.10.0.data/scripts/ptf
ptf-0.10.0.data/scripts/ptf_nn_agent.py
ptf-0.10.0.dist-info/LICENSE
ptf-0.10.0.dist-info/METADATA
ptf-0.10.0.dist-info/WHEEL
ptf-0.10.0.dist-info/top_level.txt
ptf-0.10.0.dist-info/RECORD
