Metadata-Version: 2.1
Name: ptf
Version: 0.10.0
Summary: The P4 Testing Framework
Home-page: https://github.com/p4lang/ptf
Author: P4 Developers
Author-email: p4-dev@lists.p4.org
License: Apache-2.0
Classifier: License :: OSI Approved :: Apache Software License
Classifier: Programming Language :: Python
Classifier: Programming Language :: Python :: 3
Requires-Python: >=3.4
License-File: LICENSE
